{
  "input_count": 99,
  "privacy_safe_count": 99,
  "reviews_with_pii": 10,
  "pii_detection_counts": {
    "account_id": 8,
    "order_id": 3
  },
  "affected_reviews": [
    {
      "index": 50,
      "review_id": "play_store-2026-05-20-00171",
      "pii_types": [
        "account_id"
      ]
    },
    {
      "index": 54,
      "review_id": "play_store-2026-05-19-00196",
      "pii_types": [
        "account_id"
      ]
    },
    {
      "index": 55,
      "review_id": "play_store-2026-05-19-00199",
      "pii_types": [
        "account_id"
      ]
    },
    {
      "index": 72,
      "review_id": "play_store-2026-05-19-00261",
      "pii_types": [
        "account_id"
      ]
    },
    {
      "index": 76,
      "review_id": "play_store-2026-05-19-00281",
      "pii_types": [
        "account_id"
      ]
    },
    {
      "index": 81,
      "review_id": "play_store-2026-05-18-00299",
      "pii_types": [
        "order_id"
      ]
    },
    {
      "index": 84,
      "review_id": "play_store-2026-05-18-00311",
      "pii_types": [
        "account_id"
      ]
    },
    {
      "index": 87,
      "review_id": "play_store-2026-05-18-00318",
      "pii_types": [
        "account_id"
      ]
    },
    {
      "index": 89,
      "review_id": "play_store-2026-05-18-00325",
      "pii_types": [
        "account_id",
        "order_id"
      ]
    },
    {
      "index": 93,
      "review_id": "play_store-2026-05-18-00344",
      "pii_types": [
        "order_id"
      ]
    }
  ],
  "fields_scanned": [
    "review_text",
    "review_title"
  ],
  "ready_for_ai_analysis": true,
  "remaining_pii_after_filter": []
}